<beans xmlns="http://www.springframework.org/schema/beans" xmlns:xsi="http://www.w3.org/2001/XMLSchema-instance"
	xmlns:p="http://www.springframework.org/schema/p" xmlns:dd="http://rice.kuali.org/dd"
	xsi:schemaLocation="http://www.springframework.org/schema/beans http://www.springframework.org/schema/beans/spring-beans-2.0.xsd http://rice.kuali.org/dd http://rice.kuali.org/dd/dd.xsd">

	<bean id="MileageRateObjCode" parent="MileageRateObjCode-parentBean" />
	<bean id="MileageRateObjCode-parentBean" abstract="true" parent="BusinessObjectEntry" >
		<property name="businessObjectClass" value="org.kuali.kfs.module.tem.businessobject.MileageRateObjCode" />
		<property name="lookupDefinition" ref="MileageRateObjCode-lookupDefinition" />
		<property name="inquiryDefinition" ref="MileageRateObjCode-inquiryDefinition" />
		<property name="titleAttribute" value="id" />
		<property name="objectLabel" value="MileageRateObjCode" />
		<property name="attributes">
		<list>
			<ref bean="MileageRateObjCode-id" />
			<ref bean="MileageRateObjCode-travelerTypeCode" />
			<ref bean="MileageRateObjCode-tripTypeCode" />
			<ref bean="MileageRateObjCode-mileageRateId" />
			<ref bean="MileageRateObjCode-financialObjectCode" />
			<ref bean="MileageRateObjCode-documentType" />			
			<ref bean="MileageRateObjCode-active" />
			<ref bean="MileageRateObjCode-versionNumber" />
		</list>
		</property>
		<property name="relationships">
		<list>
			<bean parent="RelationshipDefinition">
				<property name="objectAttributeName" value="travelerType" />
				<property name="primitiveAttributes">
				<list>
					<bean parent="PrimitiveAttributeDefinition" p:sourceName="travelerTypeCode" p:targetName="code" />
				</list>
				</property>
				<property name="supportAttributes">
				<list>
				</list>
				</property>
			</bean>
			<bean parent="RelationshipDefinition">
				<property name="objectAttributeName" value="tripType" />
				<property name="primitiveAttributes">
				<list>
					<bean parent="PrimitiveAttributeDefinition" p:sourceName="tripTypeCode" p:targetName="code" />
				</list>
				</property>
				<property name="supportAttributes">
				<list>
				</list>
				</property>
			</bean>
			<bean parent="RelationshipDefinition">
				<property name="objectAttributeName" value="mileageRate" />
				<property name="primitiveAttributes">
				<list>
					<bean parent="PrimitiveAttributeDefinition" p:sourceName="mileageRateId" p:targetName="id" />
				</list>
				</property>
				<property name="supportAttributes">
				<list>
				</list>
				</property>
			</bean>
		</list>
		</property>
	</bean>
	<bean id="MileageRateObjCode-id" parent="MileageRateObjCode-id-parentBean" />
	<bean id="MileageRateObjCode-id-parentBean" parent="AttributeDefinition">
		<property name="name" value="id" />
		<property name="label" value="Id" />
		<property name="shortLabel" value="Id" />
		<property name="maxLength" value="32" />
		<property name="required" value="true" />
		<property name="summary" value="Id" />
		<property name="description" value="Id" />
		<property name="control"><bean parent="HiddenControlDefinition" /></property>
		<property name="validationPattern"><bean parent="NumericValidationPattern" /></property>
	</bean>
	<bean id="MileageRateObjCode-travelerTypeCode" parent="MileageRateObjCode-travelerTypeCode-parentBean" />
	<bean id="MileageRateObjCode-travelerTypeCode-parentBean" parent="AttributeDefinition">
		<property name="name" value="travelerTypeCode" />
		<property name="label" value="Traveler Type Code" />
		<property name="shortLabel" value="Traveler Type Code" />
		<property name="maxLength" value="3" />
		<property name="required" value="true" />
		<property name="summary" value="Traveler Type Code" />
		<property name="description" value="Traveler Type Code" />
		<property name="control"><bean parent="TextControlDefinition" p:size="3"/></property>
	</bean>
	<bean id="MileageRateObjCode-tripTypeCode" parent="MileageRateObjCode-tripTypeCode-parentBean" />
	<bean id="MileageRateObjCode-tripTypeCode-parentBean" parent="AttributeDefinition">
		<property name="name" value="tripTypeCode" />
		<property name="label" value="Trip Type Code" />
		<property name="shortLabel" value="Trip Type Code" />
		<property name="maxLength" value="3" />
		<property name="required" value="true" />
		<property name="summary" value="Trip Type Code" />
		<property name="description" value="Trip Type Code" />
		<property name="control"><bean parent="TextControlDefinition" p:size="3"/></property>
	</bean>
	<bean id="MileageRateObjCode-mileageRateId" parent="MileageRateObjCode-mileageRateId-parentBean" />
	<bean id="MileageRateObjCode-mileageRateId-parentBean" parent="AttributeDefinition">
		<property name="name" value="mileageRateId" />
		<property name="label" value="Mileage Rate Id" />
		<property name="shortLabel" value="Mileage Rate Id" />
		<property name="maxLength" value="32" />
		<property name="required" value="true" />
		<property name="summary" value="Mileage Rate Id" />
		<property name="description" value="Mileage Rate Id" />
		<property name="control"><bean parent="TextControlDefinition" p:size="3"/></property>
		<property name="validationPattern"><bean parent="NumericValidationPattern" /></property>
	</bean>
	<bean id="MileageRateObjCode-financialObjectCode" parent="MileageRateObjCode-financialObjectCode-parentBean" />
	<bean id="MileageRateObjCode-financialObjectCode-parentBean" parent="AttributeDefinition">
		<property name="name" value="financialObjectCode" />
		<property name="label" value="Financial Object Code" />
		<property name="shortLabel" value="Financial Object Code" />
		<property name="maxLength" value="4" />
		<property name="required" value="true" />
		<property name="summary" value="Financial Object Code" />
		<property name="description" value="Financial Object Code" />
		<property name="control"><bean parent="TextControlDefinition" p:size="4"/></property>
	</bean>
	<bean id="MileageRateObjCode-documentType" parent="MileageRateObjCode-documentType-parentBean" />
	<bean id="MileageRateObjCode-documentType-parentBean" parent="AttributeDefinition">
		<property name="name" value="documentType" />
		<property name="label" value="Document Type" />
		<property name="shortLabel" value="Document Type" />
		<property name="maxLength" value="4" />
		<property name="required" value="true" />
		<property name="summary" value="Document Type" />
		<property name="description" value="Document Type" />
		<property name="control">
            <bean parent="SelectControlDefinition"
                p:valuesFinderClass="org.kuali.kfs.module.tem.businessobject.options.TravelDocumentTypeValuesFinder"
                p:includeKeyInLabel="false" />
        </property>
	</bean>	
	<bean id="MileageRateObjCode-active" parent="MileageRateObjCode-active-parentBean" />
	<bean id="MileageRateObjCode-active-parentBean" parent="GenericAttributes-genericBoolean">
		<property name="name" value="active" />
		<property name="label" value="Active" />
		<property name="shortLabel" value="Active" />
		<property name="required" value="true" />
		<property name="summary" value="Active" />
		<property name="description" value="Active" />
	</bean>
	<bean id="MileageRateObjCode-versionNumber" parent="MileageRateObjCode-versionNumber-parentBean" />
	<bean id="MileageRateObjCode-versionNumber-parentBean" parent="GenericAttributes-versionNumber">
		<property name="name" value="versionNumber" />
		<property name="label" value="Version Number" />
		<property name="shortLabel" value="Version Number" />
		<property name="summary" value="Version Number" />
		<property name="description" value="Version Number" />
	</bean>
	<bean id="MileageRateObjCode-inquiryDefinition" parent="MileageRateObjCode-inquiryDefinition-parentBean" />
	<bean id="MileageRateObjCode-inquiryDefinition-parentBean" abstract="true" parent="InquiryDefinition">
		<property name="title" value="Mileage Rate Obj Code Inquiry"/>
		<property name="inquirySections">
		<list>
			<bean parent="InquirySectionDefinition">
				<property name="title" value="Mileage Rate Obj Code Inquiry"/>
				<property name="numberOfColumns" value="1"/>
				<property name="inquiryFields">
				<list>
					<bean parent="FieldDefinition" p:attributeName="id" />
					<bean parent="FieldDefinition" p:attributeName="travelerTypeCode" />
					<bean parent="FieldDefinition" p:attributeName="tripTypeCode" />
					<bean parent="FieldDefinition" p:attributeName="mileageRateId" />
					<bean parent="FieldDefinition" p:attributeName="financialObjectCode" />
					<bean parent="FieldDefinition" p:attributeName="documentType" />					
					<bean parent="FieldDefinition" p:attributeName="active" />
				</list>
				</property>
			</bean>
		</list>
		</property>
	</bean>
	<bean id="MileageRateObjCode-lookupDefinition" parent="MileageRateObjCode-lookupDefinition-parentBean" />
	<bean id="MileageRateObjCode-lookupDefinition-parentBean" abstract="true" parent="LookupDefinition">
		<property name="title" value="Mileage Rate Obj Code Lookup" />
		<property name="defaultSort">
		<bean parent="SortDefinition">
			<property name="attributeNames"><list>
			</list></property>
		</bean>
		</property>
		<property name="lookupFields"><list>
			<bean parent="FieldDefinition" p:attributeName="id" />
			<bean parent="FieldDefinition" p:attributeName="travelerTypeCode" />
			<bean parent="FieldDefinition" p:attributeName="tripTypeCode" />
			<bean parent="FieldDefinition" p:attributeName="mileageRateId" />
			<bean parent="FieldDefinition" p:attributeName="financialObjectCode" />
			<bean parent="FieldDefinition" p:attributeName="documentType" />			
			<bean parent="FieldDefinition" p:attributeName="active" />
		</list>
		</property>
		<property name="resultFields">
		<list>
			<bean parent="FieldDefinition" p:attributeName="id" />
			<bean parent="FieldDefinition" p:attributeName="travelerTypeCode" />
			<bean parent="FieldDefinition" p:attributeName="tripTypeCode" />
			<bean parent="FieldDefinition" p:attributeName="mileageRateId" />
			<bean parent="FieldDefinition" p:attributeName="financialObjectCode" />
			<bean parent="FieldDefinition" p:attributeName="documentType" />			
			<bean parent="FieldDefinition" p:attributeName="active" />
		</list>
		</property>
	</bean>
</beans>