<?xml version="1.0" encoding="UTF-8"?>
<!DOCTYPE dictionaryEntry PUBLIC
    "-//Kuali Project//DTD Data Dictionary 1.0//EN"
    "../../../../core/datadictionary/dataDictionary-1_0.dtd">

<dictionaryEntry>
    <maintenanceDocument>
        <businessObjectClass>org.kuali.module.financial.bo.BankAccount</businessObjectClass>
        <maintainableClass>org.kuali.core.maintenance.KualiMaintainableImpl</maintainableClass>
        <businessRulesClass>org.kuali.module.financial.rules.BankAccountRule</businessRulesClass>
        <documentAuthorizerClass>org.kuali.core.document.MaintenanceDocumentAuthorizerBase</documentAuthorizerClass>
        <authorizations>
            <authorization action="initiate">
                <workgroups>
                    <workgroup>kualiUniversalGroup</workgroup>
                </workgroups>
            </authorization>
        </authorizations>

        <documentTypeName>KualiBankAccountMaintenanceDocument</documentTypeName>
        <documentTypeCode>BACC</documentTypeCode>

        <label>Bank Account Maintenance Document</label>
        <shortLabel>BankAcctMaintDoc</shortLabel>

        <summary>Bank Account maintenance document</summary>
        <description>Document used to create or update Bank Account objects</description>

        <lockingKeys>
            <field attributeName="financialDocumentBankCode" />
            <field attributeName="finDocumentBankAccountNumber" />
        </lockingKeys>

        <defaultExistenceChecks>
            <reference attributeName="bank" attributeToHighlightOnFail="financialDocumentBankCode" />
            <reference attributeName="cashOffsetAccount" attributeToHighlightOnFail="cashOffsetAccountNumber" activeIndicatorAttributeName="accountClosedIndicator" activeIndicatorReversed="true" />
            <reference attributeName="cashOffsetObject" attributeToHighlightOnFail="cashOffsetObjectCode" activeIndicatorAttributeName="financialObjectActiveCode" />
        </defaultExistenceChecks>

        <maintainableSections>
            <maintainableSection title="Edit Bank Account">
                <maintainableItems>
                    <maintainableField name="financialDocumentBankCode" required="true" />
                    <maintainableField name="finDocumentBankAccountNumber" required="true" />
                    <maintainableField name="finDocumentBankAccountDesc" required="true" />
                    <maintainableField name="cashOffsetFinancialChartOfAccountCode" />
                    <maintainableField name="cashOffsetAccountNumber" />
                    <maintainableField name="cashOffsetSubAccountNumber" />
                    <maintainableField name="cashOffsetObjectCode" />
                    <maintainableField name="cashOffsetSubObjectCode" />
                    <maintainableField name="versionNumber" />
                </maintainableItems>
            </maintainableSection>
        </maintainableSections>
    </maintenanceDocument>
</dictionaryEntry>