<databaseChangeLog xmlns="http://www.liquibase.org/xml/ns/dbchangelog/1.9"
	xmlns:xsi="http://www.w3.org/2001/XMLSchema-instance"
	xsi:schemaLocation="http://www.liquibase.org/xml/ns/dbchangelog/1.9 http://www.liquibase.org/xml/ns/dbchangelog/dbchangelog-1.9.xsd">

	<changeSet author="KFS50" id="NEW_CAMS_PARAMETERS">
		<comment>KFSMI-6741 Create new system parameters for KFS-CAM</comment>
		<insert tableName="KRNS_PARM_T">
			<column name="NMSPC_CD" value="KFS-CAM" />
			<column name="PARM_DTL_TYP_CD" value="ASSET" />
			<column name="PARM_NM" value="VENDOR_REQUIRED_FOR_NON_MOVEABLE_ASSET_IND" />
			<column name="OBJ_ID" value="KFSCAM102" />
			<column name="VER_NBR" valueNumeric="1" />
			<column name="PARM_TYP_CD" value="CONFG" />
			<column name="PARM_DESC_TXT"
				value="INDICATES WHETHER OR NOT THE VENDOR IS REQUIRED FOR A NON-MOVEABLE ASSET" />
			<column name="CONS_CD" value="A" />
			<column name="APPL_NMSPC_CD" value="KFS" />
		</insert>
		<insert tableName="KRNS_PARM_T">
			<column name="NMSPC_CD" value="KFS-CAM" />
			<column name="PARM_DTL_TYP_CD" value="ASSET" />
			<column name="PARM_NM"
				value="MANUFACTURER_REQUIRED_FOR_NON_MOVEABLE_ASSET_IND" />
			<column name="OBJ_ID" value="KFSCAM102" />
			<column name="VER_NBR" valueNumeric="1" />
			<column name="PARM_TYP_CD" value="CONFG" />
			<column name="PARM_DESC_TXT"
				value="INDICATES WHETHER OR NOT THE MANUFACTURER IS REQUIRED FOR A NON-MOVEABLE ASSET" />
			<column name="CONS_CD" value="A" />
			<column name="APPL_NMSPC_CD" value="KFS" />
		</insert>
		<comment>KFSMI-7158 Create CAM parameter NEW_IN_SERVICE_ASSET_DEPRECIATION_START_DATE</comment>
		<insert tableName="KRNS_PARM_T">
			<column name="NMSPC_CD" value="KFS-CAM" />
			<column name="PARM_DTL_TYP_CD" value="Asset Global" />
			<column name="PARM_NM"
				value="NEW_IN_SERVICE_ASSET_DEPRECIATION_START_DATE" />
			<column name="OBJ_ID" value="KFS684" />
			<column name="VER_NBR" valueNumeric="1" />
			<column name="PARM_TYP_CD" value="CONFG" />
			<column name="TXT" value="7/01" />
			<column name="PARM_DESC_TXT"
				value="New in service asset depreciation start date (mm/dd) used for calculating the half year depreciation convention. The half year convention will calculate the depreciation date exactly six months from this parameter date." />
			<column name="CONS_CD" value="A" />
			<column name="APPL_NMSPC_CD" value="KFS" />
		</insert>
		<insert tableName="KRNS_PARM_T">
			<column name="NMSPC_CD" value="KFS-FP" />
			<column name="PARM_DTL_TYP_CD" value="DisbursementVoucher" />
			<column name="PARM_NM" value="PAYMENT_REASON_CODE_ROYALTIES" />
			<column name="OBJ_ID" value="KFSFP298" />
			<column name="VER_NBR" valueNumeric="1" />
			<column name="PARM_TYP_CD" value="CONFG" />
			<column name="TXT" value="R" />
			<column name="PARM_DESC_TXT" value="Non Taxable Payment Reason Code - Royalties" />
			<column name="CONS_CD" value="A" />
			<column name="APPL_NMSPC_CD" value="KFS" />
		</insert>

		<insert tableName="KRNS_PARM_T">
			<column name="NMSPC_CD" value="KFS-FP" />
			<column name="PARM_DTL_TYP_CD" value="DisbursementVoucher" />
			<column name="PARM_NM" value="PAYMENT_REASON_CODE_RENTAL_PAYMENT" />
			<column name="OBJ_ID" value="KFSFP299" />
			<column name="VER_NBR" valueNumeric="1" />
			<column name="PARM_TYP_CD" value="CONFG" />
			<column name="TXT" value="T" />
			<column name="PARM_DESC_TXT"
				value="Non Taxable Payment Reason Code - Rental Payment" />
			<column name="CONS_CD" value="A" />
			<column name="APPL_NMSPC_CD" value="KFS" />
		</insert>

		<insert tableName="KRNS_PARM_T">
			<column name="NMSPC_CD" value="KFS-FP" />
			<column name="PARM_DTL_TYP_CD" value="DisbursementVoucher" />
			<column name="PARM_NM" value="PAYMENT_REASON_CODE_TRAVEL_HONORARIUM" />
			<column name="OBJ_ID" value="KFSFP300" />
			<column name="VER_NBR" valueNumeric="1" />
			<column name="PARM_TYP_CD" value="CONFG" />
			<column name="TXT" value="X" />
			<column name="PARM_DESC_TXT"
				value="Non Taxable Payment Reason Code - Travel Honorarium" />
			<column name="CONS_CD" value="A" />
			<column name="APPL_NMSPC_CD" value="KFS" />
		</insert>

		<update tableName="KRNS_PARM_T">
			<column name="TXT"
				value="customerLoadInputFileType=default.htm?turl=WordDocuments%2Fbatch.htm;customerLoadCSVInputFileType=default.htm?turl=WordDocuments%2Fbatch.htm;procurementCardInputFileType=default.htm?turl=WordDocuments%2Fbatch.htm;collectorFlatFileInputFileType=default.htm?turl=WordDocuments%2Fbatch.htm;collectorXmlInputFileType=default.htm?turl=WordDocuments%2Fbatch.htm;enterpriseFeederFileSetType=default.htm?turl=WordDocuments%2Fbatch.htm;laborEnterpriseFeederFileSetType=default.htm?turl=WordDocuments%2Fbatch.htm;assetBarcodeInventoryInputFileType=default.htm?turl=WordDocuments%2Fbatch.htm;paymentInputFileType=default.htm?turl=WordDocuments%2Fbatch.htm" />
			<where>NMSPC_CD="KFS_SYS" AND PARM_NM="BATCH_UPLOAD_HELP_URL"</where>
		</update>

		<!-- KFSMI-6867 -->
		<insert tableName="KRNS_PARM_DTL_TYP_T">
			<column name="NMSPC_CD" value="KFS-AR" />
			<column name="PARM_DTL_TYP_CD" value="CustomerBillingStatement" />
			<column name="OBJ_ID" value="KFSAR18" />
			<column name="VER_NBR" valueNumeric="1" />
			<column name="NM" value="Customer Billing Statement" />
			<column name="ACTV_IND" value="Y" />
		</insert>
		<insert tableName="KRNS_PARM_T">
			<column name="NMSPC_CD" value="KFS-AR" />
			<column name="PARM_DTL_TYP_CD" value="CustomerBillingStatement" />
			<column name="PARM_NM" value="'DUE_DATE_DAYS" />
			<column name="OBJ_ID" value="KFSAR18" />
			<column name="VER_NBR" valueNumeric="1" />
			<column name="PARM_TYP_CD" value="CONFG" />
			<column name="TXT" value="30" />
			<column name="PARM_DESC_TXT"
				value="Set the number of days that will be added to the system date to calculate the due date." />
			<column name="CONS_CD" value="A" />
			<column name="APPL_NMSPC_CD" value="KFS" />
		</insert>
		<insert tableName="KRNS_PARM_T">
			<column name="NMSPC_CD" value="KFS-AR" />
			<column name="PARM_DTL_TYP_CD" value="CustomerBillingStatement" />
			<column name="PARM_NM" value="DEFAULT_FORMAT" />
			<column name="OBJ_ID" value="KFSAR19" />
			<column name="VER_NBR" valueNumeric="1" />
			<column name="PARM_TYP_CD" value="CONFG" />
			<column name="TXT" value="SUMMARY" />
			<column name="PARM_DESC_TXT"
				value='Set this value to "SUMMARY" if you generate the summary statement as default. Set this value to "DETAIL" if you generate the detailed statement as default' />
			<column name="CONS_CD" value="A" />
			<column name="APPL_NMSPC_CD" value="KFS" />
		</insert>
		<insert tableName="KRNS_PARM_T">
			<column name="NMSPC_CD" value="KFS-PURAP" />
			<column name="PARM_DTL_TYP_CD" value="Document" />
			<column name="PARM_NM" value="DISTRIBUTION_METHOD_FOR_ACCOUNTING_LINES" />
			<column name="OBJ_ID" value="KFSPURAP6958" />
			<column name="VER_NBR" valueNumeric="1" />
			<column name="PARM_TYP_CD" value="CONFG" />
			<column name="TXT" value="S" />
			<column name="PARM_DESC_TXT"
				value='Indicates the distribution method(s) an institution will support. The values will be S (Sequential), P (Proportional), S;P (both with Sequential as default), or P;S (both, with Proportional as default). With the Sequential method account segments will be expensed/disencumbered in the order in which they appear, up to the specified dollar amount. Percentages are used on account segments to indicate how "residual" amounts are to be funded. With the Proportional method account segments will be expensed/disencumbered proportionally. Dollar amounts are used on account segments only to assist in calculating a percent distribution. Residuals will also be funded proportionally.' />
			<column name="CONS_CD" value="A" />
			<column name="APPL_NMSPC_CD" value="KFS" />
		</insert>
		<insert tableName="KRNS_PARM_T">
			<column name="NMSPC_CD" value="KFS-FP" />
			<column name="PARM_DTL_TYP_CD" value="CashReceipt" />
			<column name="PARM_NM" value="CHANGE_REQUEST_ENABLED_IND" />
			<column name="OBJ_ID" value="KFSFP6967" />
			<column name="VER_NBR" valueNumeric="1" />
			<column name="PARM_TYP_CD" value="CONFG" />
			<column name="TXT" value="Y" />
			<column name="PARM_DESC_TXT"
				value='Indicator to turn Cash receipt change request ability on and off.' />
			<column name="CONS_CD" value="A" />
			<column name="APPL_NMSPC_CD" value="KFS" />
		</insert>
		<insert tableName="KRNS_PARM_T">
			<column name="NMSPC_CD" value="KFS-FP" />
			<column name="PARM_DTL_TYP_CD" value="DisbursementVoucher" />
			<column name="PARM_NM" value="ENABLE_SEPARATION_OF_DUTIES_IND" />
			<column name="OBJ_ID" value="KFSFP4643" />
			<column name="VER_NBR" valueNumeric="1" />
			<column name="PARM_TYP_CD" value="CONFG" />
			<column name="TXT" value="Y" />
			<column name="PARM_DESC_TXT"
				value='Indicates whether separation of duties should take place when the payee is the only approver on a DV value: Y' />
			<column name="CONS_CD" value="A" />
			<column name="APPL_NMSPC_CD" value="KFS" />
		</insert>
		<insert tableName="KRNS_PARM_T">
			<column name="NMSPC_CD" value="KFS-PURAP" />
			<column name="PARM_DTL_TYP_CD" value="Document" />
			<column name="PARM_NM"
				value="COPY_ACCOUNTING_LINES_WITH_ZERO_AMOUNT_FROM_PO_TO_PREQ_IND" />
			<column name="OBJ_ID" value="KFSPURAP7033" />
			<column name="VER_NBR" valueNumeric="1" />
			<column name="PARM_TYP_CD" value="CONFG" />
			<column name="TXT" value="Y" />
			<column name="PARM_DESC_TXT"
				value='Indicates if an accounting line with zero dollar amount from Purchase Order document can be copied to Payment Request document.' />
			<column name="CONS_CD" value="A" />
			<column name="APPL_NMSPC_CD" value="KFS" />
		</insert>
		<insert tableName="KRNS_PARM_T">
			<column name="NMSPC_CD" value="KFS-PURAP" />
			<column name="PARM_DTL_TYP_CD" value="Document" />
			<column name="PARM_NM"
				value="APPROVE_ACCOUNTING_LINES_WITH_ZERO_DOLLAR_AMOUNT_IND" />
			<column name="OBJ_ID" value="KFSPURAP7033b" />
			<column name="VER_NBR" valueNumeric="1" />
			<column name="PARM_TYP_CD" value="CONFG" />
			<column name="TXT" value="Y" />
			<column name="PARM_DESC_TXT" value='' Indicates if Fiscal
				Officer can approve an accounting line that has zero dollar amount. ' />
			<column name="CONS_CD" value="A" />
			<column name="APPL_NMSPC_CD" value="KFS" />
		</insert>

		<comment>KFSMI-KFSMI-6987 Employee Benefit Expense Calculation</comment>
		<insert tableName='KRNS_PARM_T'>
			<column name='NMSPC_CD' value='KFS-SYS' />
			<column name='PARM_DTL_TYP_CD' value='All' />
			<column name='PARM_NM'
				value='ENABLE_FRINGE_BENEFIT_CALC_BY_BENEFIT_RATE_CATEGORY' />
			<column name='OBJ_ID' value='KFSLD6987a' />
			<column name='VER_NBR' valueNumeric='1' />
			<column name='PARM_TYP_CD' value='CONFG' />
			<column name='TXT' value='Y' />
			<column name='PARM_DESC_TXT'
				value='When this parameter is enabled, the fringe benefit rate calculation will be performed using the benefit category code assigned to the account and labor benefit calculation type. When the parameter is not enabled, the fringe benefit will be calculated solely based on the fringe benefit type.' />
			<column name='CONS_CD' value='A' />
			<column name='APPL_NMSPC_CD' value='KFS' />
		</insert>
		<insert tableName='KRNS_PARM_T'>
			<column name='NMSPC_CD' value='KFS-SYS' />
			<column name='PARM_DTL_TYP_CD' value='All' />
			<column name='PARM_NM' value='USE_COST_SHARE_SOURCE_ACCOUNT_BENEFIT_RATE' />
			<column name='OBJ_ID' value='KFSLD6987b' />
			<column name='VER_NBR' valueNumeric='1' />
			<column name='PARM_TYP_CD' value='CONFG' />
			<column name='TXT' value='Y' />
			<column name='PARM_DESC_TXT'
				value='When this parameter is enabled, the fringe benefit rate calculation will be performed using the benefit category code assigned to the cost share source account and labor benefit calculation type for the cost share sub-account.  When the parameter is not enabled, the fringe benefit will be calculated solely based on benefit category code assigned to the grant account associated with the sub-account.' />
			<column name='CONS_CD' value='A' />
			<column name='APPL_NMSPC_CD' value='KFS' />
		</insert>
		<insert tableName='KRNS_PARM_T'>
			<column name='NMSPC_CD' value='KFS-LD' />
			<column name='PARM_DTL_TYP_CD' value='LaborEnterpriseFeedStep' />
			<column name='PARM_NM' value='MAX_NUMBER_OF_ERRORS_ALLOWED' />
			<column name='OBJ_ID' value='KFSLD6987c' />
			<column name='VER_NBR' valueNumeric='1' />
			<column name='PARM_TYP_CD' value='CONFG' />
			<column name='TXT' value='0' />
			<column name='PARM_DESC_TXT'
				value='The number of errors allowed in the fringe and encumbrance generation process.  When the file contains beyond this number, the output file will not be created in the origin entry directory.' />
			<column name='CONS_CD' value='A' />
			<column name='APPL_NMSPC_CD' value='KFS' />
		</insert>
		<insert tableName='KRNS_PARM_T'>
			<column name='NMSPC_CD' value='KFS-LD' />
			<column name='PARM_DTL_TYP_CD' value='LaborEnterpriseFeedStep' />
			<column name='PARM_NM' value='GENERATE_FRINGE_BENEFIT' />
			<column name='OBJ_ID' value='KFSLD6987d' />
			<column name='VER_NBR' valueNumeric='1' />
			<column name='PARM_TYP_CD' value='CONFG' />
			<column name='TXT' value='Y' />
			<column name='PARM_DESC_TXT'
				value='When this parameter is Y, the fringe benefit will be generated by the Enterprise Feeder Step for the corresponding salary actual amount.' />
			<column name='CONS_CD' value='A' />
			<column name='APPL_NMSPC_CD' value='KFS' />
		</insert>
		<insert tableName='KRNS_PARM_T'>
			<column name='NMSPC_CD' value='KFS-LD' />
			<column name='PARM_DTL_TYP_CD' value='LaborEnterpriseFeedStep' />
			<column name='PARM_NM' value='GENERATE_FRINGE_BENEFIT_ENCUMBRANCE' />
			<column name='OBJ_ID' value='KFSLD6987e' />
			<column name='VER_NBR' valueNumeric='1' />
			<column name='PARM_TYP_CD' value='CONFG' />
			<column name='TXT' value='Y' />
			<column name='PARM_DESC_TXT'
				value='When this parameter is Y, the fringe benefit encumbrance will be generated by the Enterprise Feeder Step for the corresponding salary encumbrance amount.' />
			<column name='CONS_CD' value='A' />
			<column name='APPL_NMSPC_CD' value='KFS' />
		</insert>
		<insert tableName='KRNS_PARM_T'>
			<column name='NMSPC_CD' value='KFS-LD' />
			<column name='PARM_DTL_TYP_CD' value='LaborEnterpriseFeedStep' />
			<column name='PARM_NM' value='LABOR_BENEFIT_CALCULATION_OFFSET' />
			<column name='OBJ_ID' value='KFSLD7128a' />
			<column name='VER_NBR' valueNumeric='1' />
			<column name='PARM_TYP_CD' value='CONFG' />
			<column name='TXT' value='N' />
			<column name='PARM_DESC_TXT'
				value='If yes (Y), the labor benefit calculations will use an offset account to post offset entries to GL.' />
			<column name='CONS_CD' value='A' />
			<column name='APPL_NMSPC_CD' value='KFS' />
		</insert>
		<insert tableName='KRNS_PARM_T'>
			<column name='NMSPC_CD' value='KFS-LD' />
			<column name='PARM_DTL_TYP_CD' value='LaborEnterpriseFeedStep' />
			<column name='PARM_NM' value='LABOR_BENEFIT_OFFSET_DOCTYPE' />
			<column name='OBJ_ID' value='KFSLD7128b' />
			<column name='VER_NBR' valueNumeric='1' />
			<column name='PARM_TYP_CD' value='CONFG' />
			<column name='TXT' value='PAYR' />
			<column name='PARM_DESC_TXT'
				value='A list of doc types that will be used for labor benefit offset calculation.' />
			<column name='CONS_CD' value='A' />
			<column name='APPL_NMSPC_CD' value='KFS' />
		</insert>
		<insert tableName='KRNS_PARM_T'>
			<column name='NMSPC_CD' value='KFS-COA' />
			<column name='PARM_DTL_TYP_CD' value='Account' />
			<column name='PARM_NM'
				value='DEFAULT_BENEFIT_RATE_CATEGORY_CODE_BY_ACCOUNT_TYPE' />
			<column name='OBJ_ID' value='KFSLD6987f' />
			<column name='VER_NBR' valueNumeric='1' />
			<column name='PARM_TYP_CD' value='CONFG' />
			<column name='TXT' value='EN=AA;CG=BB' />
			<column name='PARM_DESC_TXT'
				value='Defines the default benefit rate category code on the account maintenance document by account type. The format is Account Type=Benefit Rate Category Code (eg. DT=AA;A1=BB, etc).' />
			<column name='CONS_CD' value='A' />
			<column name='APPL_NMSPC_CD' value='KFS' />
		</insert>
		<insert tableName='KRNS_PARM_T'>
			<column name='NMSPC_CD' value='KFS-COA' />
			<column name='PARM_DTL_TYP_CD' value='Account' />
			<column name='PARM_NM' value='DEFAULT_BENEFIT_RATE_CATEGORY_CODE' />
			<column name='OBJ_ID' value='KFSLD6987g' />
			<column name='VER_NBR' valueNumeric='1' />
			<column name='PARM_TYP_CD' value='CONFG' />
			<column name='TXT' value='--' />
			<column name='PARM_DESC_TXT'
				value='Defines the default benefit rate category code on the account maintenance document for all accounts. This default code is used when the  DEFAULT_BENEFIT_RATE_CATEGORY_CODE_BY_ACCOUNT_TYPE does not apply to an account. ÒÑÒ (two dashes) implies the category code is not applicable. The default cannot be null.' />
			<column name='CONS_CD' value='A' />
			<column name='APPL_NMSPC_CD' value='KFS' />
		</insert>

		<comment>Add fields, create parameters, permissions, and roles for KSMI-6702 Contribution</comment>

		<insert tableName="KRNS_PARM_T">
			<column name="NMSPC_CD" value="KFS-SYS" />
			<column name="PARM_DTL_TYP_CD" value="Document" />
			<column name="PARM_NM" value="ENABLE_FISCAL_PERIOD_SELECTION_IND" />
			<column name="OBJ_ID" value="KFSSYS7145-01" />
			<column name="VER_NBR" valueNumeric="1" />
			<column name="PARM_TYP_CD" value="CONFG" />
			<column name="TXT" value="Y" />
			<column name="PARM_DESC_TXT"
				value="Enables fiscal period field on financial documents for posting back to a previous period (year end processing)." />
			<column name="CONS_CD" value="A" />
			<column name="APPL_NMSPC_CD" value="KFS" />
		</insert>
		<insert tableName="KRNS_PARM_T">
			<column name="NMSPC_CD" value="KFS-SYS" />
			<column name="PARM_DTL_TYP_CD" value="Document" />
			<column name="PARM_NM" value="DECIMAL_OF_POSTBACK_PERIODS" />
			<column name="OBJ_ID" value="KFSSYS7145-02" />
			<column name="VER_NBR" valueNumeric="1" />
			<column name="PARM_TYP_CD" value="CONFG" />
			<column name="TXT" value="1" />
			<column name="PARM_DESC_TXT"
				value="Number of periods previous to the current period to allow for year end posting." />
			<column name="CONS_CD" value="A" />
			<column name="APPL_NMSPC_CD" value="KFS" />
		</insert>
		<insert tableName="KRNS_PARM_T">
			<column name="NMSPC_CD" value="KFS-SYS" />
			<column name="PARM_DTL_TYP_CD" value="Document" />
			<column name="PARM_NM" value="FISCAL_PERIOD_SELECTION_DOCUMENT_TYPES" />
			<column name="OBJ_ID" value="KFSSYS7145-03" />
			<column name="VER_NBR" valueNumeric="1" />
			<column name="PARM_TYP_CD" value="CONFG" />
			<column name="TXT"
				value="AD;AV;AVAD;AVAE;DI;DVCA;DVWF;GEC;IB;ICA;ND;SB;TF;PE;ARG;AA;AT;MPAY" />
			<column name="PARM_DESC_TXT"
				value="Document types for which the accounting period will be rendered for posting back to previous periods (year end processing). Use in conjunction with ENABLE_FISCAL_PERIOD_SELECTION_IND." />
			<column name="CONS_CD" value="A" />
			<column name="APPL_NMSPC_CD" value="KFS" />
		</insert>
		<insert tableName="KRNS_PARM_T">
			<column name="NMSPC_CD" value="KFS-CAM" />
			<column name="PARM_DTL_TYP_CD" value="Batch" />
			<column name="PARM_NM" value="INCLUDE_RETIRED_ASSETS_IND" />
			<column name="OBJ_ID" value="KFSSYS7145-04" />
			<column name="VER_NBR" valueNumeric="1" />
			<column name="PARM_TYP_CD" value="CONFG" />
			<column name="TXT" value="Y" />
			<column name="PARM_DESC_TXT"
				value="Controls whether the Year End Depreciation Job will process Retired Assets" />
			<column name="CONS_CD" value="A" />
			<column name="APPL_NMSPC_CD" value="KFS" />
		</insert>
		<insert tableName="KRNS_PARM_T">
			<column name="NMSPC_CD" value="KFS-CAM" />
			<column name="PARM_DTL_TYP_CD" value="Document" />
			<column name="PARM_NM" value="FISCAL_YEAR_END_MONTH_AND_DAY" />
			<column name="OBJ_ID" value="KFSSYS7145-05" />
			<column name="VER_NBR" valueNumeric="1" />
			<column name="PARM_TYP_CD" value="CONFG" />
			<column name="TXT" value="0630" />
			<column name="PARM_DESC_TXT"
				value="The month and day marking the last date of the fiscal year (0630 means June 30th)." />
			<column name="CONS_CD" value="A" />
			<column name="APPL_NMSPC_CD" value="KFS" />
		</insert>
		<comment>KFSMI-7172 New Parameter UNORDERED_ITEM_DEFAULT_COMMODITY_CODE and new Commodity code 99200000 </comment>
		<delete tableName="KRNS_PARM_T">
    		<where>NMSPC_CD="KFS-COA" AND PARM_DTL_TYP_CD="Account" AND PARM_NM="ACCOUNT_ADDRESS_TYPE"</where>
		</delete>
		<insert tableName="KRNS_PARM_T">
			<column name="NMSPC_CD" value="KFS-COA" />
			<column name="PARM_DTL_TYP_CD" value="Account" />
			<column name="PARM_NM" value="RESEARCH_ADMIN_ACCOUNT_ADDRESS_TYPE" />
			<column name="OBJ_ID" value="KFS606" />
			<column name="VER_NBR" valueNumeric="1" />
			<column name="PARM_TYP_CD" value="CONFG" />
			<column name="TXT" value="ADMIN;PI" />
			<column name="PARM_DESC_TXT"
				value="If KFS is integrated with a Research Admin System with multiple award address types (such as Kuali Coeus) and accounts are being automatically created based on awards in that system, this parameter defines the address type that should be populated as the account address. The first address type listed will be used if a value exists. If not the second will be used and if no address of the second type exists the address of the third type will be used, etc." />
			<column name="CONS_CD" value="A" />
			<column name="APPL_NMSPC_CD" value="KFS" />
		</insert>
		
		<comment>KFSMI- 7146 Update value for Parameter VALID_PAYEE_TYPES_BY_PAYMENT_REASON </comment>
		<update tableName="KRNS_PARM_T">
			<column name="TXT"
				value="A=V;B=V,E;C=V,E,VSP;D=V;E=V;F=V,E;G=V;H=V;K=V,VRF;L=V;M=V,E;N=V;P=V,E;R=V;T=V;W=V;X=V;Z=E" />
			<where>NMSPC_CD="KFS_FP" AND PARM_DTL_TYP_CD="DisbursementVoucher" AND PARM_NM="VALID_PAYEE_TYPES_BY_PAYMENT_REASON"</where>
		</update>
		
		<comment>KFSMI-7165 correct ACCOUNT_ADDRESS_TYPE name and description</comment>
		<insert tableName="KRNS_PARM_T">
			<column name="NMSPC_CD" value="KFS-PURAP" />
			<column name="PARM_DTL_TYP_CD" value="Purchase Order Amendment" />
			<column name="PARM_NM" value="UNORDERED_ITEM_DEFAULT_COMMODITY_CODE" />
			<column name="OBJ_ID" value="KFSPURAP7172" />
			<column name="VER_NBR" valueNumeric="1" />
			<column name="PARM_TYP_CD" value="CONFG" />
			<column name="TXT" value="99200000" />
			<column name="PARM_DESC_TXT"
				value="The default commodity code for unordered items. If commodity code is enabled and required on purchase order items, this value will be populated as the default commodity code for all unordered items when a Purchase Order Amendment Document is created from a Line Item Receiving Document." />
			<column name="CONS_CD" value="A" />
			<column name="APPL_NMSPC_CD" value="KFS" />
		</insert>
		<delete tableName="KRNS_PARM_T">
    		<where>NMSPC_CD="KFS-COA" AND PARM_DTL_TYP_CD="ObjectCode" AND PARM_NM="ENABLE_RESEARCH_ADMIN_OBJECT_CODE_ATTRIBUTE_IND"</where>
		</delete>
	</changeSet>
	

	<changeSet author="kfs50" id="KFS50CGB">
	<comment>To insert values in to the System Parameters table to help in document 
		validation of Invoice eDoc
		KRNS_PARM_T_ADD_02"</comment>
		<insert tableName="KRNS_PARM_T">
			<column name="NMSPC_CD" value="KFS-CG" />
			<column name="PARM_DTL_TYP_CD" value="AgencyAddress" />
			<column name="PARM_NM" value="DEFAULT_NUMBER_OF_COPIES_TO_PRINT" />
			<column name="OBJ_ID" value="KFSCG7200-02" />
			<column name="VER_NBR" value="1" />
			<column name="PARM_TYP_CD" value="CONFG" />
			<column name="TXT" value="1" />
			<column name="PARM_DESC_TXT"
				value="The number of invoice copies to be printed can be configured for each Agency Address. This sets the default number of copies to print for a new Agency Address." />
			<column name="CONS_CD" value="A" />
			<column name="APPL_NMSPC_CD" value="KFS" />
		</insert>
	<comment>"KRNS_PARM_T1"</comment>
		<update tableName="KRNS_PARM_T">
			<column name="PARM_DTL_TYP_CD" value="CGInvoice" />
			<where>NMSPC_CD='KFS-CG' and PARM_DTL_TYP_CD='Invoice' and
				PARM_NM='Categories'</where>
		</update>
	<comment>Inserting CGB Enhancements Indicator in to the System Parameters table
	KRNS_PARM_T_ADD_CG_VALIDATION_SWITCH </comment>
		<insert tableName="KRNS_PARM_T">
			<column name="NMSPC_CD" value="KFS-CG" />
			<column name="PARM_DTL_TYP_CD" value="All" />
			<column name="PARM_NM" value="ENABLE_CG_BILLING_ENHANCEMENTS_IND" />
			<column name="OBJ_ID" value="KFSCG7200-03" />
			<column name="VER_NBR" value="1" />
			<column name="PARM_TYP_CD" value="CONFG" />
			<column name="TXT" value="Y" />
			<column name="PARM_DESC_TXT"
				value="Set this value to Y if your institution is using the Contracts and Grants Billing enhancements. This setting will control if the validations associated with the enhancements are executed for documents." />
			<column name="CONS_CD" value="A" />
			<column name="APPL_NMSPC_CD" value="KFS" />
		</insert>
	<comment>KRNS_PARM_T_ADD_CG_MIN_INVOICE_AMOUNT</comment>
		<insert tableName="KRNS_PARM_T">
			<column name="NMSPC_CD" value="KFS-CG" />
			<column name="PARM_DTL_TYP_CD" value="Award" />
			<column name="PARM_NM" value="MINIMUM_INVOICE_AMOUNT" />
			<column name="OBJ_ID" value="KFSCG7200-04" />
			<column name="VER_NBR" value="1" />
			<column name="PARM_TYP_CD" value="CONFG" />
			<column name="TXT" value="60" />
			<column name="PARM_DESC_TXT"
				value="Minimum dollar amount required on an award for Contracts and Grants Invoicing." />
			<column name="CONS_CD" value="A" />
			<column name="APPL_NMSPC_CD" value="KFS" />
		</insert>
	<comment>Inserting CGB Enhancements Indicator in to the System Parameters table
	KRNS_PARM_T_ADD_CG_VALIDATION_SWITCH_1</comment>
		<insert tableName="KRNS_PARM_T">
			<column name="NMSPC_CD" value="KFS-CG" />
			<column name="PARM_DTL_TYP_CD" value="All" />
			<column name="PARM_NM" value="ENABLE_CG_PRORATE_BILL_IND" />
			<column name="OBJ_ID" value="KFSCG7200-05" />
			<column name="VER_NBR" value="1" />
			<column name="PARM_TYP_CD" value="CONFG" />
			<column name="TXT" value="Y" />
			<column name="PARM_DESC_TXT"
				value="Set this value to Y if your institution is using the Contracts and Grants Billing Prorate Bill function.  N otherwise." />
			<column name="CONS_CD" value="A" />
			<column name="APPL_NMSPC_CD" value="KFS" />
		</insert>
	<comment>Inserting Default processing chart code and org code to be used for 
		Cash control in to the System Parameters table
	KRNS_PARM_T_ADD_03</comment>
		<insert tableName="KRNS_PARM_T">
			<column name="NMSPC_CD" value="KFS-AR" />
			<column name="PARM_DTL_TYP_CD" value="CashControl" />
			<column name="PARM_NM" value="DEFAULT_PROCESSING_CHART" />
			<column name="OBJ_ID" value="KFSAR7200-20" />
			<column name="VER_NBR" value="1" />
			<column name="PARM_TYP_CD" value="CONFG" />
			<column name="TXT" value="UA" />
			<column name="PARM_DESC_TXT"
				value="Default value for Processing Chart code - used by LOC Batch process to set AR DOC HDR for the Cash Control Document." />
			<column name="CONS_CD" value="A" />
			<column name="APPL_NMSPC_CD" value="KFS" />
		</insert>
	<comment>KRNS_PARM_T_ADD_01</comment>
		<insert tableName="KRNS_PARM_T">
			<column name="NMSPC_CD" value="KFS-AR" />
			<column name="PARM_DTL_TYP_CD" value="CashControl" />
			<column name="PARM_NM" value="DEFAULT_PROCESSING_ORG" />
			<column name="OBJ_ID" value="KFSAR7200-21" />
			<column name="VER_NBR" value="1" />
			<column name="PARM_TYP_CD" value="CONFG" />
			<column name="TXT" value="VPIT" />
			<column name="PARM_DESC_TXT"
				value="Default value for Processing Organization code - used by LOC Batch process to set AR DOC HDR for the Cash Control Document." />
			<column name="CONS_CD" value="A" />
			<column name="APPL_NMSPC_CD" value="KFS" />
		</insert>
	<comment> Inserting Parameters for Upcoming milestones Notification job to the 
		System Parameters table
		KRNS_PARM_T_1</comment>
		<insert tableName="KRNS_PARM_T">
			<column name="NMSPC_CD" value="KFS-CG" />
			<column name="PARM_DTL_TYP_CD" value="UpcomingMilestoneNotificationStep" />
			<column name="PARM_NM" value="AWARD_MILESTONE_REMINDER_EMAIL_SUBJECT" />
			<column name="OBJ_ID" value="KFSCG7200-06" />
			<column name="VER_NBR" value="1" />
			<column name="PARM_TYP_CD" value="CONFG" />
			<column name="TXT" value="Upcoming Milestones Notification for Award." />
			<column name="PARM_DESC_TXT"
				value="Email subject line for upcoming Milestones for Award" />
			<column name="CONS_CD" value="A" />
			<column name="APPL_NMSPC_CD" value="KFS" />
		</insert>
	<comment>KRNS_PARM_T_2</comment>
		<insert tableName="KRNS_PARM_T">
			<column name="NMSPC_CD" value="KFS-CG" />
			<column name="PARM_DTL_TYP_CD" value="UpcomingMilestoneNotificationStep" />
			<column name="PARM_NM" value="AWARD_MILESTONE_CHECK_LIMIT_DAYS" />
			<column name="OBJ_ID" value="KFSCG7200-07" />
			<column name="VER_NBR" value="1" />
			<column name="PARM_TYP_CD" value="CONFG" />
			<column name="TXT" value="10" />
			<column name="PARM_DESC_TXT"
				value="No of days (limit) to check for the Upcoming Milestones for the Award." />
			<column name="CONS_CD" value="A" />
			<column name="APPL_NMSPC_CD" value="KFS" />
		</insert>

	<comment>Insert parameter for default invoicing option for awards
	KRNS_PARM_ADD_DEFAULT_INVOICE_OPTION</comment>
		<insert tableName="KRNS_PARM_T">
			<column name="NMSPC_CD" value="KFS-CG" />
			<column name="PARM_DTL_TYP_CD" value="Award" />
			<column name="PARM_NM" value="DEFAULT_INVOICING_OPTION" />
			<column name="OBJ_ID" value="KFSCG7200-08" />
			<column name="VER_NBR" value="1" />
			<column name="PARM_TYP_CD" value="CONFG" />
			<column name="TXT" value="2" />
			<column name="PARM_DESC_TXT"
				value="The default invoicing option for new Awards, where 1 = Invoice by Award, 2 = Invoice by Account, 3 = Invoice by Contract Control Account." />
			<column name="CONS_CD" value="A" />
			<column name="APPL_NMSPC_CD" value="KFS" />
		</insert>
		
	<comment>KRNS_PARM_T_ADD_206</comment>
		<insert tableName="KRNS_PARM_T">
			<column name="NMSPC_CD" value="KFS-AR" />
			<column name="PARM_DTL_TYP_CD" value="All" />
			<column name="PARM_NM" value="DEFAULT_BASIS_OF_ACCOUNTING_FOR_BILLING" />
			<column name="OBJ_ID" value="KFSAR7200-22" />
			<column name="VER_NBR" value="1" />
			<column name="PARM_TYP_CD" value="CONFG" />
			<column name="TXT" value="1" />
			<column name="PARM_DESC_TXT"
				value="This parameter defines the Basis of Accounting for filling federal forms. Value of 1 corresponds to Cash and value of 2 corresponds to Accrual." />
			<column name="CONS_CD" value="A" />
			<column name="APPL_NMSPC_CD" value="KFS" />
		</insert>
	<!-- To insert values in to the System Parameters table for defaulting Preferred 
		Billing Frequency on Agency edoc -->

	<comment>KRNS_PARM_T_ADD_DEFAULT_PREFERRED_BILLING_FREQUENCY</comment>
		<insert tableName="KRNS_PARM_T">
			<column name="NMSPC_CD" value="KFS-CG" />
			<column name="PARM_DTL_TYP_CD" value="Agency" />
			<column name="PARM_NM" value="DEFAULT_PREFERRED_BILLING_FREQUENCY" />
			<column name="OBJ_ID" value="KFSCG7200-09" />
			<column name="VER_NBR" value="1" />
			<column name="PARM_TYP_CD" value="CONFG" />
			<column name="TXT" value="MON" />
			<column name="PARM_DESC_TXT"
				value="The default value for the preferred billing frequency code for Agencies." />
			<column name="CONS_CD" value="A" />
			<column name="APPL_NMSPC_CD" value="KFS" />
		</insert>
	</changeSet></databaseChangeLog>   
      